tensor2tensor/__init__.py
tensor2tensor/problems.py
tensor2tensor/problems_test.py
tensor2tensor/bin/__init__.py
tensor2tensor/bin/make_tf_configs.py
tensor2tensor/bin/t2t_avg_all.py
tensor2tensor/bin/t2t_bleu.py
tensor2tensor/bin/t2t_datagen.py
tensor2tensor/bin/t2t_decoder.py
tensor2tensor/bin/t2t_distill.py
tensor2tensor/bin/t2t_trainer.py
tensor2tensor/bin/t2t_trainer_test.py
tensor2tensor/bin/t2t_translate_all.py
tensor2tensor/data_generators/__init__.py
tensor2tensor/data_generators/algorithmic.py
tensor2tensor/data_generators/algorithmic_math.py
tensor2tensor/data_generators/algorithmic_math_test.py
tensor2tensor/data_generators/algorithmic_test.py
tensor2tensor/data_generators/all_problems.py
tensor2tensor/data_generators/all_problems_test.py
tensor2tensor/data_generators/audio.py
tensor2tensor/data_generators/audio_test.py
tensor2tensor/data_generators/celeba.py
tensor2tensor/data_generators/cifar.py
tensor2tensor/data_generators/cipher.py
tensor2tensor/data_generators/cnn_dailymail.py
tensor2tensor/data_generators/desc2code.py
tensor2tensor/data_generators/desc2code_test.py
tensor2tensor/data_generators/dna_encoder.py
tensor2tensor/data_generators/dna_encoder_test.py
tensor2tensor/data_generators/fsns.py
tensor2tensor/data_generators/gene_expression.py
tensor2tensor/data_generators/gene_expression_test.py
tensor2tensor/data_generators/generator_utils.py
tensor2tensor/data_generators/generator_utils_test.py
tensor2tensor/data_generators/gym.py
tensor2tensor/data_generators/ice_parsing.py
tensor2tensor/data_generators/image_utils.py
tensor2tensor/data_generators/image_utils_test.py
tensor2tensor/data_generators/imagenet.py
tensor2tensor/data_generators/imdb.py
tensor2tensor/data_generators/inspect_tfrecord.py
tensor2tensor/data_generators/librispeech.py
tensor2tensor/data_generators/lm1b.py
tensor2tensor/data_generators/mnist.py
tensor2tensor/data_generators/mscoco.py
tensor2tensor/data_generators/multinli.py
tensor2tensor_test-800.0.1.dist-info/DESCRIPTION.rst
tensor2tensor_test-800.0.1.dist-info/METADATA
tensor2tensor_test-800.0.1.dist-info/RECORD
tensor2tensor_test-800.0.1.dist-info/WHEEL
tensor2tensor_test-800.0.1.dist-info/metadata.json
tensor2tensor_test-800.0.1.dist-info/top_level.txt
