Metadata-Version: 2.0
Name: tensor2tensor-test
Version: 800.0.1
Summary: Tensor2Tensor
Home-page: http://github.com/tensorflow/tensor2tensor
Author: Google Inc.
Author-email: no-reply@google.com
License: Apache 2.0
Keywords: tensorflow machine learning
Platform: UNKNOWN
Classifier: Development Status :: 4 - Beta
Classifier: Intended Audience :: Developers
Classifier: Intended Audience :: Science/Research
Classifier: License :: OSI Approved :: Apache Software License
Classifier: Topic :: Scientific/Engineering :: Artificial Intelligence
Requires-Dist: bz2file
Requires-Dist: flask
Requires-Dist: future
Requires-Dist: gevent
Requires-Dist: google-api-python-client
Requires-Dist: gunicorn
Requires-Dist: gym (<=0.9.5)
Requires-Dist: numpy
Requires-Dist: requests
Requires-Dist: scipy
Requires-Dist: sympy
Requires-Dist: six
Provides-Extra: tensorflow
Requires-Dist: tensorflow (>=1.5.0); extra == 'tensorflow'
Provides-Extra: tensorflow_gpu
Requires-Dist: tensorflow-gpu (>=1.5.0); extra == 'tensorflow_gpu'
Provides-Extra: tests
Requires-Dist: pytest; extra == 'tests'
Requires-Dist: h5py; extra == 'tests'
Requires-Dist: mock; extra == 'tests'
